dreg_client/__init__.py
dreg_client/_synth.py
dreg_client/_types.py
dreg_client/auth_service.py
dreg_client/client.py
dreg_client/image.py
dreg_client/manifest.py
dreg_client/py.typed
dreg_client/registry.py
dreg_client/repository.py
dreg_client/schemas.py
dreg_client-1.2.0.dist-info/LICENSE.txt
dreg_client-1.2.0.dist-info/METADATA
dreg_client-1.2.0.dist-info/WHEEL
dreg_client-1.2.0.dist-info/top_level.txt
dreg_client-1.2.0.dist-info/RECORD
