Metadata-Version: 2.1
Name: dreg-client
Version: 1.2.0
Summary: API client for Docker Registries
Home-page: https://github.com/djmattyg007/dreg-client
Author: Matthew Gamble
Author-email: git@matthewgamble.net
License: Apache License 2.0
Project-URL: Source, https://github.com/djmattyg007/dreg-client
Project-URL: Issues, https://github.com/djmattyg007/dreg-client/issues
Platform: UNKNOWN
Classifier: Development Status :: 5 - Production/Stable
Classifier: Intended Audience :: Developers
Classifier: Topic :: System :: Software Distribution
Classifier: License :: OSI Approved :: Apache Software License
Classifier: Operating System :: OS Independent
Classifier: Programming Language :: Python :: 3
Classifier: Programming Language :: Python :: 3.8
Classifier: Programming Language :: Python :: 3.9
Classifier: Programming Language :: Python :: 3.10
Requires-Python: >=3.8
License-File: LICENSE.txt
Requires-Dist: requests (<3.0.0,>=2.27.1)
Requires-Dist: requests-toolbelt (<0.10.0,>=0.9.1)
Provides-Extra: build
Requires-Dist: build ; extra == 'build'
Requires-Dist: twine ; extra == 'build'
Provides-Extra: dev
Requires-Dist: wheel ; extra == 'dev'
Requires-Dist: invoke ; extra == 'dev'
Requires-Dist: black ; extra == 'dev'
Requires-Dist: check-manifest ; extra == 'dev'
Requires-Dist: flake8 ; extra == 'dev'
Requires-Dist: flake8-annotations-complexity ; extra == 'dev'
Requires-Dist: flake8-black ; extra == 'dev'
Requires-Dist: flake8-breakpoint ; extra == 'dev'
Requires-Dist: flake8-bugbear ; extra == 'dev'
Requires-Dist: flake8-builtins ; extra == 'dev'
Requires-Dist: flake8-comprehensions ; extra == 'dev'
Requires-Dist: flake8-eradicate ; extra == 'dev'
Requires-Dist: flake8-expression-complexity ; extra == 'dev'
Requires-Dist: flake8-isort ; extra == 'dev'
Requires-Dist: flake8-pytest-style ; extra == 'dev'
Requires-Dist: flake8-requirements ; extra == 'dev'
Requires-Dist: isort ; extra == 'dev'
Requires-Dist: pep8-naming ; extra == 'dev'
Requires-Dist: mypy ; extra == 'dev'
Requires-Dist: types-freezegun ; extra == 'dev'
Requires-Dist: types-requests ; extra == 'dev'
Requires-Dist: coverage[toml] (<6.0,>=5.5) ; extra == 'dev'
Requires-Dist: docker (<6.0.0,>=5.0.2) ; extra == 'dev'
Requires-Dist: freezegun ; extra == 'dev'
Requires-Dist: pytest ; extra == 'dev'
Requires-Dist: pytest-cov ; extra == 'dev'
Requires-Dist: responses ; extra == 'dev'
Provides-Extra: lint
Requires-Dist: black ; extra == 'lint'
Requires-Dist: check-manifest ; extra == 'lint'
Requires-Dist: flake8 ; extra == 'lint'
Requires-Dist: flake8-annotations-complexity ; extra == 'lint'
Requires-Dist: flake8-black ; extra == 'lint'
Requires-Dist: flake8-breakpoint ; extra == 'lint'
Requires-Dist: flake8-bugbear ; extra == 'lint'
Requires-Dist: flake8-builtins ; extra == 'lint'
Requires-Dist: flake8-comprehensions ; extra == 'lint'
Requires-Dist: flake8-eradicate ; extra == 'lint'
Requires-Dist: flake8-expression-complexity ; extra == 'lint'
Requires-Dist: flake8-isort ; extra == 'lint'
Requires-Dist: flake8-pytest-style ; extra == 'lint'
Requires-Dist: flake8-requirements ; extra == 'lint'
Requires-Dist: isort ; extra == 'lint'
Requires-Dist: pep8-naming ; extra == 'lint'
Provides-Extra: test
Requires-Dist: coverage[toml] (<6.0,>=5.5) ; extra == 'test'
Requires-Dist: docker (<6.0.0,>=5.0.2) ; extra == 'test'
Requires-Dist: freezegun ; extra == 'test'
Requires-Dist: pytest ; extra == 'test'
Requires-Dist: pytest-cov ; extra == 'test'
Requires-Dist: responses ; extra == 'test'
Provides-Extra: typecheck
Requires-Dist: mypy ; extra == 'typecheck'
Requires-Dist: types-freezegun ; extra == 'typecheck'
Requires-Dist: types-requests ; extra == 'typecheck'
